panther/__init__.py
panther/__main__.py
panther/banner.py
panther/generate_certificates.sh
panther/config/__init__.py
panther/config/config_experiment_schema.py
panther/config/config_global_schema.py
panther/config/config_manager.py
panther/core/__init__.py
panther/core/experiment_manager.py
panther/core/experiment_strategy.py
panther/core/exceptions/EnvironmentPluginNotFound.py
panther/core/exceptions/ServicePluginNotFound.py
panther/core/exceptions/TesterPluginNotFound.py
panther/core/exceptions/__init__.py
panther/core/observer/__init__.py
panther/core/observer/event.py
panther/core/observer/event_manager.py
panther/core/observer/experiment_observer.py
panther/core/observer/gui_observer.py
panther/core/observer/logger_observer.py
panther/core/observer/observer_interface.py
panther/core/observer/result_observer.py
panther/core/results/__init__.py
panther/core/results/result_collector.py
panther/core/results/result_handler.py
panther/core/results/result_handlers/__init__.py
panther/core/results/result_handlers/local_storage_handler.py
panther/core/results/result_handlers/parser_handler.py
panther/core/results/result_handlers/storage_handler.py
panther/core/results/result_handlers/validation_handler.py
panther/core/test_cases/__init__.py
panther/core/test_cases/test_case.py
panther/core/test_cases/test_interface.py
panther/core/utils/__init__.py
panther/core/utils/docker_builder.py
panther/core/utils/jinja_manager.py
panther/plugins/README.md
panther/plugins/__init__.py
panther/plugins/plugin_interface.py
panther/plugins/plugin_loader.py
panther/plugins/plugin_manager.py
panther/plugins/environments/__init__.py
panther/plugins/environments/config_schema.py
panther/plugins/environments/environment_interface.py
panther/plugins/environments/execution_environment/__init__.py
panther/plugins/environments/execution_environment/config_schema.py
panther/plugins/environments/execution_environment/execution_environment_interface.py
panther_net-0.0.1.dist-info/LICENSE
panther_net-0.0.1.dist-info/METADATA
panther_net-0.0.1.dist-info/WHEEL
panther_net-0.0.1.dist-info/entry_points.txt
panther_net-0.0.1.dist-info/top_level.txt
panther_net-0.0.1.dist-info/RECORD
