Metadata-Version: 2.1
Name: panther-net
Version: 0.0.1
Summary: Panther: Protocol formal Analysis and formal Network Threat Evaluation Resources
Author-email: ElNiak <christophe.crochet.researcher@gmail.com>
License: MIT
Project-URL: repository, https://github.com/ElNiak/PANTHER
Project-URL: ivy, https://github.com/ElNiak/PANTHER-Ivy
Classifier: Programming Language :: Python :: 3
Classifier: License :: OSI Approved :: MIT License
Classifier: Operating System :: OS Independent
Requires-Python: >=3.8
License-File: LICENSE
Requires-Dist: omegaconf
Requires-Dist: cerberus
Requires-Dist: jinja2
Requires-Dist: requests
Requires-Dist: PyYAML
Requires-Dist: docker
Requires-Dist: termcolor
Requires-Dist: terminal_banner
Requires-Dist: flask
Requires-Dist: flask_session
Requires-Dist: flask_wtf
Requires-Dist: django
Requires-Dist: flask-socketio
Requires-Dist: Flask-Cors==4.0.1
Requires-Dist: npf-web-extension
Requires-Dist: execnet
Requires-Dist: pexpect
Requires-Dist: chardet
Requires-Dist: gperf
Requires-Dist: pandas
Requires-Dist: scandir
Requires-Dist: ply
Requires-Dist: plantuml
Requires-Dist: scapy
Requires-Dist: importlib_metadata
Provides-Extra: tests
Requires-Dist: pytest; extra == "tests"
Requires-Dist: pytest-cov; extra == "tests"
Requires-Dist: hypothesis; extra == "tests"
Requires-Dist: pytest-mock; extra == "tests"
Provides-Extra: lint
Requires-Dist: black; extra == "lint"
Requires-Dist: flake8; extra == "lint"
Provides-Extra: doc
Requires-Dist: mkdocs; extra == "doc"
Requires-Dist: mkdocs-material; extra == "doc"
Requires-Dist: mkdocs-minify-plugin; extra == "doc"
Requires-Dist: mkdocs-git-revision-date-localized-plugin; extra == "doc"
Requires-Dist: mkdocs-git-authors-plugin; extra == "doc"
Requires-Dist: mkdocs-table-reader-plugin; extra == "doc"
Requires-Dist: mkdocs-img2fig-plugin; extra == "doc"
Requires-Dist: mknotebooks; extra == "doc"
Requires-Dist: mkdocs-awesome-pages-plugin; extra == "doc"
Requires-Dist: mkdocs-enumerate-headings-plugin; extra == "doc"
Requires-Dist: mkdocs-print-site-plugin; extra == "doc"
Requires-Dist: mkgendocs; extra == "doc"
Requires-Dist: markdown-callouts; extra == "doc"
Requires-Dist: mkdocs-coverage; extra == "doc"
Requires-Dist: mkdocs-material; extra == "doc"
Requires-Dist: mkdocs-gen-files; extra == "doc"
Requires-Dist: mkdocs-literate-nav; extra == "doc"
Requires-Dist: mkdocstrings; extra == "doc"
Requires-Dist: PyYAML==6.0.1; extra == "doc"
Requires-Dist: pymdown-extensions; extra == "doc"
Requires-Dist: mkdocs-material-extensions; extra == "doc"
Requires-Dist: mkdocs-gen-files; extra == "doc"
Requires-Dist: mkdocs-literate-nav; extra == "doc"
Requires-Dist: mkdocs-section-index; extra == "doc"
Requires-Dist: mkdocstrings[python]; extra == "doc"
Requires-Dist: mkdocs-exclude; extra == "doc"
Requires-Dist: mkdocs-same-dir; extra == "doc"
